{
  "domain": "ecology",
  "timestamp": "2026-02-21T07:41:37.250427+00:00",
  "n_words": 70,
  "core": [
    "abiotic",
    "biocoenosis",
    "biodiversity",
    "biome",
    "biotic",
    "canopy",
    "carnivore",
    "climax community",
    "commensalism",
    "competition",
    "cosmopolitan",
    "decomposer",
    "detritivore",
    "ecesis",
    "ecosystem",
    "ecotone",
    "ecotype",
    "endemic",
    "epiphyte",
    "establishment",
    "eutrophication",
    "fauna",
    "flora",
    "food web",
    "guild",
    "habitat",
    "herbivore",
    "heterotroph",
    "keystone species",
    "microhabitat",
    "mutualism",
    "mycorrhizae",
    "niche",
    "omnivore",
    "parasitism",
    "photosynthesis",
    "phytoplankton",
    "pioneer species",
    "population density",
    "predation",
    "primary producer",
    "scavenger",
    "succession",
    "symbiosis",
    "trophic level",
    "understory",
    "zooplankton"
  ],
  "peripheral": [
    "adaptation",
    "association",
    "biomass",
    "boundary",
    "carrying capacity",
    "colonization",
    "community",
    "density",
    "dispersal",
    "disturbance",
    "diversity",
    "dominance",
    "gradient",
    "immigration",
    "invasion",
    "migration",
    "mortality",
    "natality",
    "recruitment",
    "resilience",
    "resistance",
    "richness",
    "territory"
  ],
  "words": [
    "abiotic",
    "adaptation",
    "association",
    "biocoenosis",
    "biodiversity",
    "biomass",
    "biome",
    "biotic",
    "boundary",
    "canopy",
    "carnivore",
    "carrying capacity",
    "climax community",
    "colonization",
    "commensalism",
    "community",
    "competition",
    "cosmopolitan",
    "decomposer",
    "density",
    "detritivore",
    "dispersal",
    "disturbance",
    "diversity",
    "dominance",
    "ecesis",
    "ecosystem",
    "ecotone",
    "ecotype",
    "endemic",
    "epiphyte",
    "establishment",
    "eutrophication",
    "fauna",
    "flora",
    "food web",
    "gradient",
    "guild",
    "habitat",
    "herbivore",
    "heterotroph",
    "immigration",
    "invasion",
    "keystone species",
    "microhabitat",
    "migration",
    "mortality",
    "mutualism",
    "mycorrhizae",
    "natality",
    "niche",
    "omnivore",
    "parasitism",
    "photosynthesis",
    "phytoplankton",
    "pioneer species",
    "population density",
    "predation",
    "primary producer",
    "recruitment",
    "resilience",
    "resistance",
    "richness",
    "scavenger",
    "succession",
    "symbiosis",
    "territory",
    "trophic level",
    "understory",
    "zooplankton"
  ]
}